<chart>
        <draw>
        <!-- Title -->
        <text transition='slide_left' 
        delay='1' 
        duration='0.5' 
        color='cc9900' 
        alpha='200' 
        font='arial' 
        bold='true' 
        size='40' x='-60' y='0' 
        width='520' 
        height='50' 
        h_align='right' 
        v_align='middle'>Moodle downloads </text>

        <text transition='slide_right' 
        delay='1' 
        duration='0.5' 
        color='000000' 
        alpha='40' 
        font='arial' 
        bold='true' 
        size='20' x='130' y='30' 
        width='320' 
        height='50' 
        h_align='right'  
        v_align='middle'>Downloads per month</text>
        
        <!-- image (JPEG or SWF) -->
        <image  layer='background'
        url='images/download.jpg'
        x='80'
        y='100'
        height='200'
        width='200'
        alpha='30'
        />     
        </draw>

        <chart_transition type='scale'
        delay='1'
        duration='2'
        order='series' />

        <axis_category size='10' 
        color='000000'  
        font='arial' 
        bold='true' 
        skip='0'
        alpha='50'
        orientation='vertical_down' />

        <axis_value min='0'
        font='arial' 
        bold='true' 
        size='10' 
        color='000000' 
        alpha='50' 
        steps='6' 
        prefix='' 
        suffix='' 
        decimals='0' 
        separator='' 
        show_min='true' />

        <chart_pref line_thickness='4'   
        point_shape='none' 
        fill_shape='boolean' />

        <!-- series preferences -->
        <series_color>
        <color>FF0000</color>
        </series_color>

        <!-- show cursor/ mouse over value -->
        <chart_value position='cursor' size='12' color='000000' alpha='75' />

        <chart_border color='000000'
        top_thickness='2' 
        bottom_thickness='2' 
        left_thickness='2' 
        right_thickness='2' />

        <!-- legend pref -->
        <legend_label 
        size='10'
        />

        <legend_rect x='-100' 
        y='-100' 
        width='5' 
        height='5' 
        margin='5' />
        
        <chart_type> column</chart_type>
        <chart_data>
          <row>
	<string>J 2004</string>
	<string>J 2004</string>
	<string>A 2004</string>
	<string>S 2004</string>
	<string>O 2004</string>
	<string>N 2004</string>
	<string>D 2004</string>
	<string>J 2005</string>
	<string>F 2005</string>
	<string>M 2005</string>
	<string>A 2005</string>
	<string>M 2005</string>
	<string>J 2005</string>
	<string>J 2005</string>
	<string>A 2005</string>
	<string>S 2005</string>
	<string>O 2005</string>
	<string>N 2005</string>
	<string>D 2005</string>
	<string>J 2006</string>
	<string>F 2006</string>
	<string>M 2006</string>
	<string>A 2006</string>
	<string>M 2006</string>
	<string>J 2006</string>
	<string>J 2006</string>
	<string>A 2006</string>
	<string>S 2006</string>
	<string>O 2006</string>
	<string>N 2006</string>
	<string>D 2006</string>
	<string>J 2007</string>
	<string>F 2007</string>
	<string>M 2007</string>
	<string>A 2007</string>
	<string>M 2007</string>
	<string>J 2007</string>
	<string>J 2007</string>
	<string>A 2007</string>
	<string>S 2007</string>
	<string>O 2007</string>
	<string>N 2007</string>
	<string>D 2007</string>
	<string>J 2008</string>
	<string>F 2008</string>
	<string>M 2008</string>
	<string>A 2008</string>
	<string>M 2008</string>
	<string>J 2008</string>
	<string>J 2008</string>
	<string>A 2008</string>
	<string>S 2008</string>
	<string>O 2008</string>
	<string>N 2008</string>
	<string>D 2008</string>
	<string>J 2009</string>
	<string>F 2009</string>
	<string>M 2009</string>
	<string>A 2009</string>
	<string>M 2009</string>
	<string>J 2009</string>
	<string>J 2009</string>
	<string>A 2009</string>
	<string>S 2009</string>
	<string>O 2009</string>
	<string>N 2009</string>
	<string>D 2009</string>
	<string>J 2010</string>
	<string>F 2010</string>
	<string>M 2010</string>
	<string>A 2010</string>
	<string>M 2010</string>
	<string>J 2010</string>
	<string>J 2010</string>
	<string>A 2010</string>
	<string>S 2010</string>
	<string>O 2010</string>
	<string>N 2010</string>
	<string>D 2010</string>
	<string>J 2011</string>
	<string>F 2011</string>
	<string>M 2011</string>
	<string>A 2011</string>
	<string>M 2011</string>
          </row>
          <row>
            <number>33268</number>
            <number>17060</number>
            <number>20167</number>
            <number>23235</number>
            <number>21741</number>
            <number>25016</number>
            <number>20975</number>
            <number>23043</number>
            <number>28889</number>
            <number>31122</number>
            <number>28818</number>
            <number>48576</number>
            <number>33813</number>
            <number>33442</number>
            <number>27012</number>
            <number>31892</number>
            <number>43040</number>
            <number>45442</number>
            <number>36920</number>
            <number>32644</number>
            <number>37792</number>
            <number>43227</number>
            <number>38145</number>
            <number>39879</number>
            <number>44729</number>
            <number>45128</number>
            <number>38896</number>
            <number>46039</number>
            <number>49149</number>
            <number>56470</number>
            <number>52150</number>
            <number>39395</number>
            <number>69802</number>
            <number>57254</number>
            <number>58274</number>
            <number>53323</number>
            <number>53850</number>
            <number>54983</number>
            <number>45267</number>
            <number>53572</number>
            <number>60478</number>
            <number>96414</number>
            <number>54550</number>
            <number>56321</number>
            <number>62704</number>
            <number>89012</number>
            <number>84427</number>
            <number>78187</number>
            <number>74224</number>
            <number>76071</number>
            <number>70743</number>
            <number>85110</number>
            <number>93652</number>
            <number>82670</number>
            <number>55186</number>
            <number>78969</number>
            <number>88557</number>
            <number>93579</number>
            <number>84829</number>
            <number>90974</number>
            <number>87366</number>
            <number>84869</number>
            <number>80870</number>
            <number>95971</number>
            <number>127052</number>
            <number>166108</number>
            <number>151128</number>
            <number>158518</number>
            <number>154865</number>
            <number>174534</number>
            <number>162691</number>
            <number>155895</number>
            <number>146844</number>
            <number>123712</number>
            <number>122745</number>
            <number>114965</number>
            <number>112893</number>
            <number>136261</number>
            <number>114077</number>
            <number>133220</number>
            <number>141520</number>
            <number>149977</number>
            <number>118287</number>
            <number>119588</number>
         </row>
</chart_data> 
 </chart>